toonet/__init__.py
toonet-0.0.1.dist-info/METADATA
toonet-0.0.1.dist-info/WHEEL
toonet-0.0.1.dist-info/top_level.txt
toonet-0.0.1.dist-info/RECORD
