Metadata-Version: 2.4
Name: toonet
Version: 0.0.1
Summary: TooNet: A non-profit open-world query initiative, part of the TOO project.
Author-email: TooNet Team <hi@toonet.ai>
Project-URL: Homepage, https://toonet.ai
Project-URL: Bug Tracker, https://github.com/toonet/toonet/issues
Project-URL: Source, https://github.com/toonet
Classifier: Development Status :: 3 - Alpha
Classifier: Intended Audience :: Developers
Classifier: Topic :: Scientific/Engineering :: Artificial Intelligence
Classifier: License :: OSI Approved :: MIT License
Classifier: Programming Language :: Python :: 3
Requires-Python: >=3.7
